AguaAlert/__init__.py
AguaAlert/analisis.py
AguaAlert/main_menu.py
AguaAlert/pozos.py
AguaAlert/prediccion.py
AguaAlert/reportes.py
AguaAlert/visualizacion.py
AguaAlert-0.1.1.dist-info/LICENSE
AguaAlert-0.1.1.dist-info/METADATA
AguaAlert-0.1.1.dist-info/WHEEL
AguaAlert-0.1.1.dist-info/top_level.txt
AguaAlert-0.1.1.dist-info/RECORD
