Metadata-Version: 2.1
Name: AguaAlert
Version: 0.1.1
Summary: Sistema de predicción de niveles de aguas subterráneas utilizando datos de precipitación.
Home-page: https://github.com/yourusername/AguaAlert
Author: José Rodríguez, Anderson Pineda, Andriana Espinoza, Cesar Villavicencio, Jhon Castillo
Author-email: jdrodriguez30@utpl.edu.ec
Classifier: Programming Language :: Python :: 3
Classifier: License :: OSI Approved :: MIT License
Classifier: Operating System :: OS Independent
Requires-Python: >=3.6
License-File: LICENSE
Requires-Dist: numpy ==1.24.1
Requires-Dist: matplotlib
Requires-Dist: pandas
Requires-Dist: scikit-learn
Requires-Dist: statsmodels
Requires-Dist: scipy
Requires-Dist: openpyxl
